lazyerrors/__init__.py
lazyerrors/error.py
lazyerrors-0.0.3.dist-info/LICENSE.txt
lazyerrors-0.0.3.dist-info/METADATA
lazyerrors-0.0.3.dist-info/WHEEL
lazyerrors-0.0.3.dist-info/top_level.txt
lazyerrors-0.0.3.dist-info/RECORD
